crossword_solver/__init__.py
eight_puzzle/__init__.py
shortest_path/__init__.py
sudoku_solver/__init__.py
sudoku_solver/utils.py
aiml_lab-0.1.dist-info/LICENSE
aiml_lab-0.1.dist-info/METADATA
aiml_lab-0.1.dist-info/WHEEL
aiml_lab-0.1.dist-info/top_level.txt
aiml_lab-0.1.dist-info/RECORD
